fino2py/__init__.py
fino2py/cleaning/__init__.py
fino2py/cleaning/merge_split_data.py
fino2py/dependencies.py
fino2py/ingesting/__init__.py
fino2py/ingesting/read_nova_demographics.py
fino2py/ingesting/read_raw_demographics.py
fino2py/ingesting/read_raw_finometer_data.py
fino2py/ingesting/read_raw_nova_data.py
fino2py/reshaping/__init__.py
fino2py/reshaping/create_chunk.py
fino2py/reshaping/generate_protocol_averages.py
fino2py/reshaping/minute_by_minute.py
fino2py/reshaping/minute_by_minute_from_folder.py
fino2py/reshaping/nova_concat.py
fino2py/reshaping/nova_minute_by_minute.py
fino2py/times/__init__.py
fino2py/times/convert_fino_time.py
fino2py/times/convert_partial_time.py
fino2py/times/convert_timestamp_time.py
fino2py/times/import_protocol_times.py
fino2py-0.1.0.7.dist-info/LICENSE
fino2py-0.1.0.7.dist-info/METADATA
fino2py-0.1.0.7.dist-info/WHEEL
fino2py-0.1.0.7.dist-info/RECORD
