Metadata-Version: 2.1
Name: fino2py
Version: 0.1.0.7
Summary: A package to help researchers and clinicians work with data produced by the Finapress Finometer and Nova devices
Author: Kev O'Malley
Requires-Python: >=3.11,<4.0
Classifier: Programming Language :: Python :: 3
Classifier: Programming Language :: Python :: 3.11
Classifier: Programming Language :: Python :: 3.12
Requires-Dist: pandas (>=2.0.1,<3.0.0)
